[
  {
    "Id": "5ebee488-ee91-4a57-971e-7ef5d8cff1d9",
    "Name": "Jens Peter Ottosen",
    "Bookings": [
      {
        "Date": "2022-05-14T00:00:00+02:00",
        "TimeSlot": 0,
        "Tables": 1
      },
      {
        "Date": "2022-05-14T00:00:00+02:00",
        "TimeSlot": 0,
        "Tables": 1
      }
    ]
  },
  {
    "Id": "8727237e-083b-4dbd-a173-7c217b68c647",
    "Name": "Mikkeline Torsten",
    "Bookings": [
      {
        "Date": "2022-05-16T00:00:00+02:00",
        "TimeSlot": 1,
        "Tables": 1
      },
      {
        "Date": "2022-05-18T00:00:00+02:00",
        "TimeSlot": 0,
        "Tables": 1
      },
      {
        "Date": "2022-05-23T00:00:00+02:00",
        "TimeSlot": 0,
        "Tables": 2
      }
    ]
  },
  {
    "Id": "2f1a9861-5e87-4a65-acfc-90cb1990f6ac",
    "Name": "Bjarne Troels",
    "Bookings": [
      {
        "Date": "2022-05-22T00:00:00+02:00",
        "TimeSlot": 1,
        "Tables": 1
      },
      {
        "Date": "2022-05-18T00:00:00+02:00",
        "TimeSlot": 1,
        "Tables": 1
      },
      {
        "Date": "2022-05-21T00:00:00+02:00",
        "TimeSlot": 1,
        "Tables": 2
      }
    ]
  },
  {
    "Id": "721c3ec6-95e7-46e2-9acf-00fae98f99b4",
    "Name": "Iben Rosa",
    "Bookings": [
      {
        "Date": "2022-05-22T00:00:00+02:00",
        "TimeSlot": 1,
        "Tables": 1
      },
      {
        "Date": "2022-05-14T00:00:00+02:00",
        "TimeSlot": 0,
        "Tables": 2
      }
    ]
  },
  {
    "Id": "d71ec6ba-4601-4b72-86d1-621ac0b1be39",
    "Name": "Hanna Grethe",
    "Bookings": [
      {
        "Date": "2022-05-14T00:00:00+02:00",
        "TimeSlot": 0,
        "Tables": 1
      }
    ]
  },
  {
    "Id": "104265b5-ac30-42dd-b844-1d561379b48d",
    "Name": "Åse Birgersen",
    "Bookings": [
      {
        "Date": "2022-05-26T00:00:00+02:00",
        "TimeSlot": 1,
        "Tables": 3
      },
      {
        "Date": "2022-05-26T00:00:00+02:00",
        "TimeSlot": 1,
        "Tables": 1
      }
    ]
  },
  {
    "Id": "a28abe46-b88d-4a90-a315-cafd69f4b8a8",
    "Name": "Valdemar Tilde",
    "Bookings": [
      {
        "Date": "2022-05-27T00:00:00+02:00",
        "TimeSlot": 1,
        "Tables": 1
      }
    ]
  },
  {
    "Id": "2da9d94c-936a-4cfb-8b09-7c9219dcf44d",
    "Name": "Mathias Ester",
    "Bookings": [
      {
        "Date": "2022-05-25T00:00:00+02:00",
        "TimeSlot": 0,
        "Tables": 1
      }
    ]
  },
  {
    "Id": "3a1c256b-5f13-45f8-be45-baad94151414",
    "Name": "Karolina Stig",
    "Bookings": [
      {
        "Date": "2022-05-20T00:00:00+02:00",
        "TimeSlot": 1,
        "Tables": 1
      }
    ]
  },
  {
    "Id": "611d34eb-1413-476e-9f11-a4a576f4f23c",
    "Name": "Jannik Halfdan",
    "Bookings": [
      {
        "Date": "2022-05-27T00:00:00+02:00",
        "TimeSlot": 0,
        "Tables": 1
      }
    ]
  }
]
